wagtail_redirect_importer/__init__.py
wagtail_redirect_importer/admin_urls.py
wagtail_redirect_importer/admin_views.py
wagtail_redirect_importer/apps.py
wagtail_redirect_importer/base_formats.py
wagtail_redirect_importer/forms.py
wagtail_redirect_importer/tmp_storages.py
wagtail_redirect_importer/wagtail_hooks.py
wagtail_redirect_importer/management/__init__.py
wagtail_redirect_importer/management/commands/__init__.py
wagtail_redirect_importer/management/commands/import_redirects.py
wagtail_redirect_importer/migrations/__init__.py
wagtail_redirect_importer/static/wagtail_redirect_importer/css/index.css
wagtail_redirect_importer/templates/wagtail_redirect_importer/choose_file.html
wagtail_redirect_importer/templates/wagtail_redirect_importer/confirm_import.html
wagtail_redirect_importer/templates/wagtail_redirect_importer/import_summary.html
wagtail_redirect_importer-1.0.2.dist-info/LICENSE
wagtail_redirect_importer-1.0.2.dist-info/METADATA
wagtail_redirect_importer-1.0.2.dist-info/WHEEL
wagtail_redirect_importer-1.0.2.dist-info/top_level.txt
wagtail_redirect_importer-1.0.2.dist-info/RECORD
