Metadata-Version: 2.1
Name: wagtail-redirect-importer
Version: 1.0.2
Summary: Lets you import redirects into Wagtail from different tabular data formats (like .csv, xls, xlsx)
Home-page: https://github.com/Frojd/wagtail-redirect-importer
Author: Fröjd
Author-email: martin@marteinn.se
License: MIT
Keywords: wagtail_redirect_importer
Platform: UNKNOWN
Classifier: Development Status :: 3 - Alpha
Classifier: Framework :: Django :: 2.1
Classifier: Intended Audience :: Developers
Classifier: License :: OSI Approved :: MIT License
Classifier: Natural Language :: English
Classifier: Programming Language :: Python :: 3
Classifier: Programming Language :: Python :: 3.5
Classifier: Programming Language :: Python :: 3.6
Classifier: Topic :: Utilities
Classifier: Framework :: Wagtail
Classifier: Framework :: Wagtail :: 2
Requires-Dist: tablib[xls,xlsx]
